skippy/__init__.py
skippy/data/__init__.py
skippy/data/decorator.py
skippy/data/minio.py
skippy/data/priorities.py
skippy/data/redis.py
skippy/data/storage.py
skippy/data/utils.py
skippy/tests/__init__.py
skippy/tests/main.py
skippy/tests/function/__init__.py
skippy_data-0.89.dist-info/METADATA
skippy_data-0.89.dist-info/WHEEL
skippy_data-0.89.dist-info/top_level.txt
skippy_data-0.89.dist-info/RECORD
