Metadata-Version: 2.1
Name: skippy-data
Version: 0.89
Summary: look up data
Home-page: https://git.dsg.tuwien.ac.at/c.marcelino/skippy-data
Author: Cynthia Marcelino
Author-email: keniack@gmail.com
License: UNKNOWN
Download-URL: https://git.dsg.tuwien.ac.at/c.marcelino/skippy-data
Platform: UNKNOWN
Classifier: Programming Language :: Python :: 3
Classifier: License :: OSI Approved :: MIT License
Classifier: Operating System :: OS Independent
Requires-Dist: kubernetes (~=12.0.1)
Requires-Dist: minio (~=5.0.10)
Requires-Dist: redis (~=3.5.3)
Requires-Dist: PyYAML (~=5.3.1)
